{
  "export_id": "dff90f41-a8cd-4788-bea6-0e8a25dd5dcb",
  "created_at": "2026-07-07T06:25:49.997216+00:00",
  "name": "Governance Test Export",
  "scope": "local_research",
  "research_only": true,
  "offline_only": true,
  "shadow_only": true,
  "no_production_influence": true,
  "not_eligible_for_promotion": true,
  "source_candidate_id": null,
  "source_benchmark_report_id": null,
  "candidate_metadata": null,
  "benchmark_metadata": null,
  "row_count": 23,
  "date_range": {
    "start": "2026-03-16",
    "end": "2026-04-15"
  },
  "export_format": "jsonl",
  "feature_schema": [
    "price",
    "engine_score"
  ],
  "target_schema": [
    "next_price",
    "realized_return"
  ],
  "warning_schema": [],
  "checksum": "72e2f009f64a03b263d1ffc0ee9f0693",
  "fingerprint": "df691b27b2197923",
  "safety_flags": {
    "research_only": true,
    "offline_only": true,
    "shadow_only": true,
    "no_production_influence": true,
    "not_eligible_for_promotion": true
  },
  "limitations": [
    "Research-only, offline-only, shadow-only dataset.",
    "Not used by production recommendations.",
    "Not eligible for promotion.",
    "No broker execution.",
    "No real-time production signal generation."
  ],
  "warnings": []
}