{
  "export_id": "fc7daf14-6695-493a-bc48-8a2d239b5b3b",
  "created_at": "2026-07-06T12:38:36.182396+00:00",
  "name": "Governance Test Export",
  "scope": "local_research",
  "research_only": true,
  "offline_only": true,
  "shadow_only": true,
  "no_production_influence": true,
  "not_eligible_for_promotion": true,
  "source_candidate_id": null,
  "source_benchmark_report_id": null,
  "candidate_metadata": null,
  "benchmark_metadata": null,
  "row_count": 23,
  "date_range": {
    "start": "2026-03-16",
    "end": "2026-04-15"
  },
  "export_format": "jsonl",
  "feature_schema": [
    "price",
    "engine_score"
  ],
  "target_schema": [
    "next_price",
    "realized_return"
  ],
  "warning_schema": [],
  "checksum": "fd8ef7ec6d646ae5f8ae35ed23e1abc5",
  "fingerprint": "53a81bc4ee52fd2c",
  "safety_flags": {
    "research_only": true,
    "offline_only": true,
    "shadow_only": true,
    "no_production_influence": true,
    "not_eligible_for_promotion": true
  },
  "limitations": [
    "Research-only, offline-only, shadow-only dataset.",
    "Not used by production recommendations.",
    "Not eligible for promotion.",
    "No broker execution.",
    "No real-time production signal generation."
  ],
  "warnings": []
}